RiskLib/Option.py
RiskLib/VaR.py
RiskLib/__init__.py
RiskLib/calculation.py
RiskLib/cov_matrix.py
RiskLib/linear_regression.py
RiskLib/optimal_portfolio.py
RiskLib/risk_attribution.py
RiskLib/risk_parity.py
RiskLib/simulation.py
RiskLib-0.7.1.dist-info/METADATA
RiskLib-0.7.1.dist-info/WHEEL
RiskLib-0.7.1.dist-info/top_level.txt
RiskLib-0.7.1.dist-info/RECORD
